watch_import/__init__.py
watch_import/module.py
watch_import-0.0.2.dist-info/LICENSE
watch_import-0.0.2.dist-info/METADATA
watch_import-0.0.2.dist-info/WHEEL
watch_import-0.0.2.dist-info/entry_points.txt
watch_import-0.0.2.dist-info/top_level.txt
watch_import-0.0.2.dist-info/RECORD
