Metadata-Version: 2.1
Name: watch_import
Version: 0.0.2
Summary: Watch target file/folder for changes in python files and import/reimport
Author: Daniel Sundberg
License: Copyright 2024 Daniel Sundberg
Keywords: import,reimport,save
Classifier: Programming Language :: Python :: 3
Classifier: License :: OSI Approved :: MIT License
Requires-Python: >=3.8
License-File: LICENSE
Requires-Dist: watchfiles
